scikit_learn_lambda/__init__.py
scikit_learn_lambda/cache.py
scikit_learn_lambda/lib.py
scikit_learn_lambda/s3_url.py
scikit_learn_lambda-0.1.0.dist-info/METADATA
scikit_learn_lambda-0.1.0.dist-info/WHEEL
scikit_learn_lambda-0.1.0.dist-info/top_level.txt
scikit_learn_lambda-0.1.0.dist-info/RECORD
